{
  "@context": "http://schemas.frictionlessdata.io/fiscal-data-package.jsonld",
  "author": "PresupuestoAbierto CostaRica",
  "bytes": 187765572,
  "count_of_rows": 341233,
  "countryCode": "CR",
  "description": "Presupuesto de Egresos 2018 Costa Rica (enero - diciembre).",
  "fiscalPeriod": {
    "end": "2018-12-31",
    "start": "2018-01-01"
  },
  "hash": "25ff6418df06c5f3b1614dfd9dfa4521",
  "model": {
    "dimensions": {
      "administrative-classification": {
        "attributes": {
          "programa_codigo": {
            "parent": "titulo_codigo",
            "source": "programa_codigo",
            "title": "Programa_Codigo"
          },
          "programa_descripcion": {
            "labelfor": "programa_codigo",
            "source": "programa_descripcion",
            "title": "Programa_Descripcion"
          },
          "subprograma_codigo": {
            "parent": "programa_codigo",
            "source": "subprograma_codigo",
            "title": "Subprograma_Codigo"
          },
          "subprograma_descripcion": {
            "labelfor": "subprograma_codigo",
            "source": "subprograma_descripcion",
            "title": "Subprograma_Descripcion"
          },
          "titulo_codigo": {
            "source": "titulo_codigo",
            "title": "Titulo_Codigo"
          },
          "titulo_descripcion": {
            "labelfor": "titulo_codigo",
            "source": "titulo_descripcion",
            "title": "Titulo_Descripcion"
          }
        },
        "classificationType": "administrative",
        "dimensionType": "classification",
        "primaryKey": [
          "titulo_codigo",
          "programa_codigo",
          "subprograma_codigo"
        ]
      },
      "date": {
        "attributes": {
          "ejercicio": {
            "source": "ejercicio",
            "title": "Ejercicio"
          }
        },
        "dimensionType": "datetime",
        "primaryKey": [
          "ejercicio"
        ]
      },
      "economic-classification": {
        "attributes": {
          "ce_grupo_codigo": {
            "parent": "ce_partida_codigo",
            "source": "ce_grupo_codigo",
            "title": "CE_Grupo_Codigo"
          },
          "ce_grupo_descripcion": {
            "labelfor": "ce_grupo_codigo",
            "source": "ce_grupo_descripcion",
            "title": "CE_Grupo_Descripcion"
          },
          "ce_partida_codigo": {
            "source": "ce_partida_codigo",
            "title": "CE_Partida_Codigo"
          },
          "ce_partida_descripcion": {
            "labelfor": "ce_partida_codigo",
            "source": "ce_partida_descripcion",
            "title": "CE_Partida_Descripcion"
          },
          "ce_renglon_codigo": {
            "parent": "ce_subpartida_codigo",
            "source": "ce_renglon_codigo",
            "title": "CE_Renglon_Codigo"
          },
          "ce_renglon_descripcion": {
            "labelfor": "ce_renglon_codigo",
            "source": "ce_renglon_descripcion",
            "title": "CE_Renglon_Descripcion"
          },
          "ce_subpartida_codigo": {
            "parent": "ce_grupo_codigo",
            "source": "ce_subpartida_codigo",
            "title": "CE_Subpartida_Codigo"
          },
          "ce_subpartida_descripcion": {
            "labelfor": "ce_subpartida_codigo",
            "source": "ce_subpartida_descripcion",
            "title": "CE_Subpartida_Descripcion"
          }
        },
        "classificationType": "economic",
        "dimensionType": "classification",
        "primaryKey": [
          "ce_partida_codigo",
          "ce_grupo_codigo",
          "ce_subpartida_codigo",
          "ce_renglon_codigo"
        ]
      },
      "fin-source": {
        "attributes": {
          "ff_codigo": {
            "source": "ff_codigo",
            "title": "FF_CODIGO"
          },
          "ff_descripcion": {
            "labelfor": "ff_codigo",
            "source": "ff_descripcion",
            "title": "FF_Descripcion"
          }
        },
        "dimensionType": "other",
        "primaryKey": [
          "ff_codigo"
        ]
      },
      "functional-classification": {
        "attributes": {
          "cf_clase_codigo": {
            "source": "cf_clase_codigo",
            "title": "CF_Clase_Codigo"
          },
          "cf_clase_descripcion": {
            "labelfor": "cf_clase_codigo",
            "source": "cf_clase_descripcion",
            "title": "CF_Clase_Descripcion"
          },
          "cf_grupo_codigo": {
            "parent": "cf_subclase_codigo",
            "source": "cf_grupo_codigo",
            "title": "CF_Grupo_Codigo"
          },
          "cf_grupo_descripcion": {
            "labelfor": "cf_grupo_codigo",
            "source": "cf_grupo_descripcion",
            "title": "CF_Grupo_Descripcion"
          },
          "cf_subclase_codigo": {
            "parent": "cf_clase_codigo",
            "source": "cf_subclase_codigo",
            "title": "CF_Subclase_Codigo"
          },
          "cf_subclase_descripcion": {
            "labelfor": "cf_subclase_codigo",
            "source": "cf_subclase_descripcion",
            "title": "CF_Subclase_Descripcion"
          },
          "cf_subgrupo_codigo": {
            "parent": "cf_grupo_codigo",
            "source": "cf_subgrupo_codigo",
            "title": "CF_Subgrupo_Codigo"
          },
          "cf_subgrupo_descripcion": {
            "labelfor": "cf_subgrupo_codigo",
            "source": "cf_subgrupo_descripcion",
            "title": "CF_Subgrupo_Descripcion"
          }
        },
        "classificationType": "functional",
        "dimensionType": "classification",
        "primaryKey": [
          "cf_clase_codigo",
          "cf_subclase_codigo",
          "cf_grupo_codigo",
          "cf_subgrupo_codigo"
        ]
      },
      "unknown": {
        "attributes": {
          "cog_grupo_codigo": {
            "source": "cog_grupo_codigo",
            "title": "COG_Grupo_Codigo"
          },
          "cog_grupo_descripcion": {
            "labelfor": "cog_grupo_codigo",
            "source": "cog_grupo_descripcion",
            "title": "COG_Grupo_Descripcion"
          },
          "cog_partida_codigo": {
            "source": "cog_partida_codigo",
            "title": "COG_Partida_Codigo"
          },
          "cog_partida_descripcion": {
            "labelfor": "cog_partida_codigo",
            "source": "cog_partida_descripcion",
            "title": "COG_Partida_Descripcion"
          },
          "cog_subpartida_codigo": {
            "source": "cog_subpartida_codigo",
            "title": "COG_Subpartida_Codigo"
          },
          "cog_subpartida_descripcion": {
            "labelfor": "cog_subpartida_codigo",
            "source": "cog_subpartida_descripcion",
            "title": "COG_Subpartida_Descripcion"
          },
          "ff_clase1": {
            "source": "ff_clase1",
            "title": "FF_Clase1"
          },
          "ff_clase2": {
            "source": "ff_clase2",
            "title": "FF_Clase2"
          },
          "mes": {
            "source": "mes",
            "title": "Mes"
          }
        },
        "dimensionType": "other",
        "primaryKey": [
          "cog_partida_codigo",
          "cog_grupo_codigo",
          "cog_subpartida_codigo"
        ]
      }
    },
    "measures": {
      "co_monto": {
        "source": "co_monto",
        "title": "CO_Monto"
      },
      "de_monto": {
        "source": "de_monto",
        "title": "DE_Monto"
      },
      "li_monto": {
        "source": "li_monto",
        "title": "LI_Monto"
      },
      "pa_monto": {
        "source": "pa_monto",
        "title": "PA_Monto"
      },
      "pi_monto": {
        "source": "pi_monto",
        "title": "PI_Monto"
      },
      "pp_monto": {
        "source": "pp_monto",
        "title": "PP_Monto"
      },
      "rm_monto": {
        "source": "rm_monto",
        "title": "RM_Monto"
      },
      "so_monto": {
        "source": "so_monto",
        "title": "SO_Monto"
      }
    }
  },
  "name": "egreso_2018_cr",
  "owner": "2e6c7fb02a09883c5556f341e814d3bf",
  "profile": "data-package",
  "profiles": {
    "fiscal": "*",
    "tabular": "*"
  },
  "promise": {},
  "regionCode": "na",
  "resources": [
    {
      "bytes": 140824170,
      "count_of_rows": 255924,
      "dialect": {
        "delimiter": ",",
        "doubleQuote": true,
        "lineTerminator": "\r\n",
        "quoteChar": "\"",
        "skipInitialSpace": false
      },
      "dpp:streamedFrom": "/tmp/tmpvouk7zdn/final/data/egreso2018ene_dic.csv",
      "encoding": "utf-8",
      "format": "csv",
      "hash": "a24feb4ea8195f28361cd2acec8bcfea",
      "mediatype": "text/csv",
      "name": "egreso2018ene_dic",
      "path": "data/egreso2018ene_dic.csv",
      "profile": "data-resource",
      "schema": {
        "fields": [
          {
            "columnType": "date:fiscal-year",
            "conceptType": "date",
            "format": "default",
            "name": "ejercicio",
            "slug": "ejercicio",
            "title": "Ejercicio",
            "type": "integer"
          },
          {
            "columnType": "unknown:string",
            "conceptType": "unknown",
            "format": "default",
            "name": "mes",
            "slug": "mes",
            "title": "Mes",
            "type": "string"
          },
          {
            "columnType": "administrative-classification:generic:level1:code",
            "conceptType": "administrative-classification",
            "format": "default",
            "name": "titulo_codigo",
            "slug": "titulo_codigo",
            "title": "Titulo_Codigo",
            "type": "string"
          },
          {
            "columnType": "administrative-classification:generic:level1:label",
            "conceptType": "administrative-classification",
            "format": "default",
            "name": "titulo_descripcion",
            "slug": "titulo_descripcion",
            "title": "Titulo_Descripcion",
            "type": "string"
          },
          {
            "columnType": "administrative-classification:generic:level2:code",
            "conceptType": "administrative-classification",
            "format": "default",
            "name": "programa_codigo",
            "slug": "programa_codigo",
            "title": "Programa_Codigo",
            "type": "string"
          },
          {
            "columnType": "administrative-classification:generic:level2:label",
            "conceptType": "administrative-classification",
            "format": "default",
            "name": "programa_descripcion",
            "slug": "programa_descripcion",
            "title": "Programa_Descripcion",
            "type": "string"
          },
          {
            "columnType": "administrative-classification:generic:level3:code",
            "conceptType": "administrative-classification",
            "format": "default",
            "name": "subprograma_codigo",
            "slug": "subprograma_codigo",
            "title": "Subprograma_Codigo",
            "type": "string"
          },
          {
            "columnType": "administrative-classification:generic:level3:label",
            "conceptType": "administrative-classification",
            "format": "default",
            "name": "subprograma_descripcion",
            "slug": "subprograma_descripcion",
            "title": "Subprograma_Descripcion",
            "type": "string"
          },
          {
            "columnType": "unknown:string-1:code",
            "conceptType": "unknown",
            "format": "default",
            "name": "cog_partida_codigo",
            "slug": "cog_partida_codigo",
            "title": "COG_Partida_Codigo",
            "type": "string"
          },
          {
            "columnType": "unknown:string-1:label",
            "conceptType": "unknown",
            "format": "default",
            "name": "cog_partida_descripcion",
            "slug": "cog_partida_descripcion",
            "title": "COG_Partida_Descripcion",
            "type": "string"
          },
          {
            "columnType": "unknown:string-2:code",
            "conceptType": "unknown",
            "format": "default",
            "name": "cog_grupo_codigo",
            "slug": "cog_grupo_codigo",
            "title": "COG_Grupo_Codigo",
            "type": "string"
          },
          {
            "columnType": "unknown:string-2:label",
            "conceptType": "unknown",
            "format": "default",
            "name": "cog_grupo_descripcion",
            "slug": "cog_grupo_descripcion",
            "title": "COG_Grupo_Descripcion",
            "type": "string"
          },
          {
            "columnType": "unknown:string-3:code",
            "conceptType": "unknown",
            "format": "default",
            "name": "cog_subpartida_codigo",
            "slug": "cog_subpartida_codigo",
            "title": "COG_Subpartida_Codigo",
            "type": "string"
          },
          {
            "columnType": "unknown:string-3:label",
            "conceptType": "unknown",
            "format": "default",
            "name": "cog_subpartida_descripcion",
            "slug": "cog_subpartida_descripcion",
            "title": "COG_Subpartida_Descripcion",
            "type": "string"
          },
          {
            "columnType": "economic-classification:generic:level1:code",
            "conceptType": "economic-classification",
            "format": "default",
            "name": "ce_partida_codigo",
            "slug": "ce_partida_codigo",
            "title": "CE_Partida_Codigo",
            "type": "string"
          },
          {
            "columnType": "economic-classification:generic:level1:label",
            "conceptType": "economic-classification",
            "format": "default",
            "name": "ce_partida_descripcion",
            "slug": "ce_partida_descripcion",
            "title": "CE_Partida_Descripcion",
            "type": "string"
          },
          {
            "columnType": "economic-classification:generic:level2:code",
            "conceptType": "economic-classification",
            "format": "default",
            "name": "ce_grupo_codigo",
            "slug": "ce_grupo_codigo",
            "title": "CE_Grupo_Codigo",
            "type": "string"
          },
          {
            "columnType": "economic-classification:generic:level2:label",
            "conceptType": "economic-classification",
            "format": "default",
            "name": "ce_grupo_descripcion",
            "slug": "ce_grupo_descripcion",
            "title": "CE_Grupo_Descripcion",
            "type": "string"
          },
          {
            "columnType": "economic-classification:generic:level3:code",
            "conceptType": "economic-classification",
            "format": "default",
            "name": "ce_subpartida_codigo",
            "slug": "ce_subpartida_codigo",
            "title": "CE_Subpartida_Codigo",
            "type": "string"
          },
          {
            "columnType": "economic-classification:generic:level3:label",
            "conceptType": "economic-classification",
            "format": "default",
            "name": "ce_subpartida_descripcion",
            "slug": "ce_subpartida_descripcion",
            "title": "CE_Subpartida_Descripcion",
            "type": "string"
          },
          {
            "columnType": "economic-classification:generic:level4:code",
            "conceptType": "economic-classification",
            "format": "default",
            "name": "ce_renglon_codigo",
            "slug": "ce_renglon_codigo",
            "title": "CE_Renglon_Codigo",
            "type": "string"
          },
          {
            "columnType": "economic-classification:generic:level4:label",
            "conceptType": "economic-classification",
            "format": "default",
            "name": "ce_renglon_descripcion",
            "slug": "ce_renglon_descripcion",
            "title": "CE_Renglon_Descripcion",
            "type": "string"
          },
          {
            "columnType": "functional-classification:generic:level1:code",
            "conceptType": "functional-classification",
            "format": "default",
            "name": "cf_clase_codigo",
            "slug": "cf_clase_codigo",
            "title": "CF_Clase_Codigo",
            "type": "string"
          },
          {
            "columnType": "functional-classification:generic:level1:label",
            "conceptType": "functional-classification",
            "format": "default",
            "name": "cf_clase_descripcion",
            "slug": "cf_clase_descripcion",
            "title": "CF_Clase_Descripcion",
            "type": "string"
          },
          {
            "columnType": "functional-classification:generic:level2:code",
            "conceptType": "functional-classification",
            "format": "default",
            "name": "cf_subclase_codigo",
            "slug": "cf_subclase_codigo",
            "title": "CF_Subclase_Codigo",
            "type": "string"
          },
          {
            "columnType": "functional-classification:generic:level2:label",
            "conceptType": "functional-classification",
            "format": "default",
            "name": "cf_subclase_descripcion",
            "slug": "cf_subclase_descripcion",
            "title": "CF_Subclase_Descripcion",
            "type": "string"
          },
          {
            "columnType": "functional-classification:generic:level3:code",
            "conceptType": "functional-classification",
            "format": "default",
            "name": "cf_grupo_codigo",
            "slug": "cf_grupo_codigo",
            "title": "CF_Grupo_Codigo",
            "type": "string"
          },
          {
            "columnType": "functional-classification:generic:level3:label",
            "conceptType": "functional-classification",
            "format": "default",
            "name": "cf_grupo_descripcion",
            "slug": "cf_grupo_descripcion",
            "title": "CF_Grupo_Descripcion",
            "type": "string"
          },
          {
            "columnType": "functional-classification:generic:level4:code",
            "conceptType": "functional-classification",
            "format": "default",
            "name": "cf_subgrupo_codigo",
            "slug": "cf_subgrupo_codigo",
            "title": "CF_Subgrupo_Codigo",
            "type": "string"
          },
          {
            "columnType": "functional-classification:generic:level4:label",
            "conceptType": "functional-classification",
            "format": "default",
            "name": "cf_subgrupo_descripcion",
            "slug": "cf_subgrupo_descripcion",
            "title": "CF_Subgrupo_Descripcion",
            "type": "string"
          },
          {
            "columnType": "fin-source:generic:code",
            "conceptType": "fin-source",
            "format": "default",
            "name": "ff_codigo",
            "slug": "ff_codigo",
            "title": "FF_CODIGO",
            "type": "string"
          },
          {
            "columnType": "fin-source:generic:label",
            "conceptType": "fin-source",
            "format": "default",
            "name": "ff_descripcion",
            "slug": "ff_descripcion",
            "title": "FF_Descripcion",
            "type": "string"
          },
          {
            "columnType": "unknown:string",
            "conceptType": "unknown",
            "format": "default",
            "name": "ff_clase1",
            "slug": "ff_clase1",
            "title": "FF_Clase1",
            "type": "string"
          },
          {
            "columnType": "unknown:string",
            "conceptType": "unknown",
            "format": "default",
            "name": "ff_clase2",
            "slug": "ff_clase2",
            "title": "FF_Clase2",
            "type": "string"
          },
          {
            "columnType": "value",
            "conceptType": "value",
            "decimalChar": ".",
            "format": "default",
            "groupChar": "",
            "name": "pi_monto",
            "slug": "pi_monto",
            "title": "PI_Monto",
            "type": "number"
          },
          {
            "columnType": "value",
            "conceptType": "value",
            "decimalChar": ".",
            "format": "default",
            "groupChar": "",
            "name": "pp_monto",
            "slug": "pp_monto",
            "title": "PP_Monto",
            "type": "number"
          },
          {
            "columnType": "value",
            "conceptType": "value",
            "decimalChar": ".",
            "format": "default",
            "groupChar": "",
            "name": "li_monto",
            "slug": "li_monto",
            "title": "LI_Monto",
            "type": "number"
          },
          {
            "columnType": "value",
            "conceptType": "value",
            "decimalChar": ".",
            "format": "default",
            "groupChar": "",
            "name": "so_monto",
            "slug": "so_monto",
            "title": "SO_Monto",
            "type": "number"
          },
          {
            "columnType": "value",
            "conceptType": "value",
            "decimalChar": ".",
            "format": "default",
            "groupChar": "",
            "name": "co_monto",
            "slug": "co_monto",
            "title": "CO_Monto",
            "type": "number"
          },
          {
            "columnType": "value",
            "conceptType": "value",
            "decimalChar": ".",
            "format": "default",
            "groupChar": "",
            "name": "rm_monto",
            "slug": "rm_monto",
            "title": "RM_Monto",
            "type": "number"
          },
          {
            "columnType": "value",
            "conceptType": "value",
            "decimalChar": ".",
            "format": "default",
            "groupChar": "",
            "name": "de_monto",
            "slug": "de_monto",
            "title": "DE_Monto",
            "type": "number"
          },
          {
            "columnType": "value",
            "conceptType": "value",
            "decimalChar": ".",
            "format": "default",
            "groupChar": "",
            "name": "pa_monto",
            "slug": "pa_monto",
            "title": "PA_Monto",
            "type": "number"
          }
        ],
        "primaryKey": [
          "ejercicio",
          "titulo_codigo",
          "programa_codigo",
          "subprograma_codigo",
          "cog_partida_codigo",
          "cog_grupo_codigo",
          "cog_subpartida_codigo",
          "ce_partida_codigo",
          "ce_grupo_codigo",
          "ce_subpartida_codigo",
          "ce_renglon_codigo",
          "cf_clase_codigo",
          "cf_subclase_codigo",
          "cf_grupo_codigo",
          "cf_subgrupo_codigo",
          "ff_codigo"
        ]
      }
    },
    {
      "bytes": 93882780,
      "count_of_rows": 170616,
      "dialect": {
        "delimiter": ",",
        "doubleQuote": true,
        "lineTerminator": "\r\n",
        "quoteChar": "\"",
        "skipInitialSpace": false
      },
      "dpp:streamedFrom": "/tmp/tmpvouk7zdn/final/data/egreso2018ene_dic__2018.csv",
      "encoding": "utf-8",
      "format": "csv",
      "hash": "a24feb4ea8195f28361cd2acec8bcfea",
      "mediatype": "text/csv",
      "name": "egreso2018ene_dic__2018",
      "path": "data/egreso2018ene_dic__2018.csv",
      "profile": "data-resource",
      "schema": {
        "fields": [
          {
            "columnType": "date:fiscal-year",
            "conceptType": "date",
            "format": "default",
            "name": "ejercicio",
            "slug": "ejercicio",
            "title": "Ejercicio",
            "type": "integer"
          },
          {
            "columnType": "unknown:string",
            "conceptType": "unknown",
            "format": "default",
            "name": "mes",
            "slug": "mes",
            "title": "Mes",
            "type": "string"
          },
          {
            "columnType": "administrative-classification:generic:level1:code",
            "conceptType": "administrative-classification",
            "format": "default",
            "name": "titulo_codigo",
            "slug": "titulo_codigo",
            "title": "Titulo_Codigo",
            "type": "string"
          },
          {
            "columnType": "administrative-classification:generic:level1:label",
            "conceptType": "administrative-classification",
            "format": "default",
            "name": "titulo_descripcion",
            "slug": "titulo_descripcion",
            "title": "Titulo_Descripcion",
            "type": "string"
          },
          {
            "columnType": "administrative-classification:generic:level2:code",
            "conceptType": "administrative-classification",
            "format": "default",
            "name": "programa_codigo",
            "slug": "programa_codigo",
            "title": "Programa_Codigo",
            "type": "string"
          },
          {
            "columnType": "administrative-classification:generic:level2:label",
            "conceptType": "administrative-classification",
            "format": "default",
            "name": "programa_descripcion",
            "slug": "programa_descripcion",
            "title": "Programa_Descripcion",
            "type": "string"
          },
          {
            "columnType": "administrative-classification:generic:level3:code",
            "conceptType": "administrative-classification",
            "format": "default",
            "name": "subprograma_codigo",
            "slug": "subprograma_codigo",
            "title": "Subprograma_Codigo",
            "type": "string"
          },
          {
            "columnType": "administrative-classification:generic:level3:label",
            "conceptType": "administrative-classification",
            "format": "default",
            "name": "subprograma_descripcion",
            "slug": "subprograma_descripcion",
            "title": "Subprograma_Descripcion",
            "type": "string"
          },
          {
            "columnType": "unknown:string-1:code",
            "conceptType": "unknown",
            "format": "default",
            "name": "cog_partida_codigo",
            "slug": "cog_partida_codigo",
            "title": "COG_Partida_Codigo",
            "type": "string"
          },
          {
            "columnType": "unknown:string-1:label",
            "conceptType": "unknown",
            "format": "default",
            "name": "cog_partida_descripcion",
            "slug": "cog_partida_descripcion",
            "title": "COG_Partida_Descripcion",
            "type": "string"
          },
          {
            "columnType": "unknown:string-2:code",
            "conceptType": "unknown",
            "format": "default",
            "name": "cog_grupo_codigo",
            "slug": "cog_grupo_codigo",
            "title": "COG_Grupo_Codigo",
            "type": "string"
          },
          {
            "columnType": "unknown:string-2:label",
            "conceptType": "unknown",
            "format": "default",
            "name": "cog_grupo_descripcion",
            "slug": "cog_grupo_descripcion",
            "title": "COG_Grupo_Descripcion",
            "type": "string"
          },
          {
            "columnType": "unknown:string-3:code",
            "conceptType": "unknown",
            "format": "default",
            "name": "cog_subpartida_codigo",
            "slug": "cog_subpartida_codigo",
            "title": "COG_Subpartida_Codigo",
            "type": "string"
          },
          {
            "columnType": "unknown:string-3:label",
            "conceptType": "unknown",
            "format": "default",
            "name": "cog_subpartida_descripcion",
            "slug": "cog_subpartida_descripcion",
            "title": "COG_Subpartida_Descripcion",
            "type": "string"
          },
          {
            "columnType": "economic-classification:generic:level1:code",
            "conceptType": "economic-classification",
            "format": "default",
            "name": "ce_partida_codigo",
            "slug": "ce_partida_codigo",
            "title": "CE_Partida_Codigo",
            "type": "string"
          },
          {
            "columnType": "economic-classification:generic:level1:label",
            "conceptType": "economic-classification",
            "format": "default",
            "name": "ce_partida_descripcion",
            "slug": "ce_partida_descripcion",
            "title": "CE_Partida_Descripcion",
            "type": "string"
          },
          {
            "columnType": "economic-classification:generic:level2:code",
            "conceptType": "economic-classification",
            "format": "default",
            "name": "ce_grupo_codigo",
            "slug": "ce_grupo_codigo",
            "title": "CE_Grupo_Codigo",
            "type": "string"
          },
          {
            "columnType": "economic-classification:generic:level2:label",
            "conceptType": "economic-classification",
            "format": "default",
            "name": "ce_grupo_descripcion",
            "slug": "ce_grupo_descripcion",
            "title": "CE_Grupo_Descripcion",
            "type": "string"
          },
          {
            "columnType": "economic-classification:generic:level3:code",
            "conceptType": "economic-classification",
            "format": "default",
            "name": "ce_subpartida_codigo",
            "slug": "ce_subpartida_codigo",
            "title": "CE_Subpartida_Codigo",
            "type": "string"
          },
          {
            "columnType": "economic-classification:generic:level3:label",
            "conceptType": "economic-classification",
            "format": "default",
            "name": "ce_subpartida_descripcion",
            "slug": "ce_subpartida_descripcion",
            "title": "CE_Subpartida_Descripcion",
            "type": "string"
          },
          {
            "columnType": "economic-classification:generic:level4:code",
            "conceptType": "economic-classification",
            "format": "default",
            "name": "ce_renglon_codigo",
            "slug": "ce_renglon_codigo",
            "title": "CE_Renglon_Codigo",
            "type": "string"
          },
          {
            "columnType": "economic-classification:generic:level4:label",
            "conceptType": "economic-classification",
            "format": "default",
            "name": "ce_renglon_descripcion",
            "slug": "ce_renglon_descripcion",
            "title": "CE_Renglon_Descripcion",
            "type": "string"
          },
          {
            "columnType": "functional-classification:generic:level1:code",
            "conceptType": "functional-classification",
            "format": "default",
            "name": "cf_clase_codigo",
            "slug": "cf_clase_codigo",
            "title": "CF_Clase_Codigo",
            "type": "string"
          },
          {
            "columnType": "functional-classification:generic:level1:label",
            "conceptType": "functional-classification",
            "format": "default",
            "name": "cf_clase_descripcion",
            "slug": "cf_clase_descripcion",
            "title": "CF_Clase_Descripcion",
            "type": "string"
          },
          {
            "columnType": "functional-classification:generic:level2:code",
            "conceptType": "functional-classification",
            "format": "default",
            "name": "cf_subclase_codigo",
            "slug": "cf_subclase_codigo",
            "title": "CF_Subclase_Codigo",
            "type": "string"
          },
          {
            "columnType": "functional-classification:generic:level2:label",
            "conceptType": "functional-classification",
            "format": "default",
            "name": "cf_subclase_descripcion",
            "slug": "cf_subclase_descripcion",
            "title": "CF_Subclase_Descripcion",
            "type": "string"
          },
          {
            "columnType": "functional-classification:generic:level3:code",
            "conceptType": "functional-classification",
            "format": "default",
            "name": "cf_grupo_codigo",
            "slug": "cf_grupo_codigo",
            "title": "CF_Grupo_Codigo",
            "type": "string"
          },
          {
            "columnType": "functional-classification:generic:level3:label",
            "conceptType": "functional-classification",
            "format": "default",
            "name": "cf_grupo_descripcion",
            "slug": "cf_grupo_descripcion",
            "title": "CF_Grupo_Descripcion",
            "type": "string"
          },
          {
            "columnType": "functional-classification:generic:level4:code",
            "conceptType": "functional-classification",
            "format": "default",
            "name": "cf_subgrupo_codigo",
            "slug": "cf_subgrupo_codigo",
            "title": "CF_Subgrupo_Codigo",
            "type": "string"
          },
          {
            "columnType": "functional-classification:generic:level4:label",
            "conceptType": "functional-classification",
            "format": "default",
            "name": "cf_subgrupo_descripcion",
            "slug": "cf_subgrupo_descripcion",
            "title": "CF_Subgrupo_Descripcion",
            "type": "string"
          },
          {
            "columnType": "fin-source:generic:code",
            "conceptType": "fin-source",
            "format": "default",
            "name": "ff_codigo",
            "slug": "ff_codigo",
            "title": "FF_CODIGO",
            "type": "string"
          },
          {
            "columnType": "fin-source:generic:label",
            "conceptType": "fin-source",
            "format": "default",
            "name": "ff_descripcion",
            "slug": "ff_descripcion",
            "title": "FF_Descripcion",
            "type": "string"
          },
          {
            "columnType": "unknown:string",
            "conceptType": "unknown",
            "format": "default",
            "name": "ff_clase1",
            "slug": "ff_clase1",
            "title": "FF_Clase1",
            "type": "string"
          },
          {
            "columnType": "unknown:string",
            "conceptType": "unknown",
            "format": "default",
            "name": "ff_clase2",
            "slug": "ff_clase2",
            "title": "FF_Clase2",
            "type": "string"
          },
          {
            "columnType": "value",
            "conceptType": "value",
            "decimalChar": ".",
            "format": "default",
            "groupChar": "",
            "name": "pi_monto",
            "slug": "pi_monto",
            "title": "PI_Monto",
            "type": "number"
          },
          {
            "columnType": "value",
            "conceptType": "value",
            "decimalChar": ".",
            "format": "default",
            "groupChar": "",
            "name": "pp_monto",
            "slug": "pp_monto",
            "title": "PP_Monto",
            "type": "number"
          },
          {
            "columnType": "value",
            "conceptType": "value",
            "decimalChar": ".",
            "format": "default",
            "groupChar": "",
            "name": "li_monto",
            "slug": "li_monto",
            "title": "LI_Monto",
            "type": "number"
          },
          {
            "columnType": "value",
            "conceptType": "value",
            "decimalChar": ".",
            "format": "default",
            "groupChar": "",
            "name": "so_monto",
            "slug": "so_monto",
            "title": "SO_Monto",
            "type": "number"
          },
          {
            "columnType": "value",
            "conceptType": "value",
            "decimalChar": ".",
            "format": "default",
            "groupChar": "",
            "name": "co_monto",
            "slug": "co_monto",
            "title": "CO_Monto",
            "type": "number"
          },
          {
            "columnType": "value",
            "conceptType": "value",
            "decimalChar": ".",
            "format": "default",
            "groupChar": "",
            "name": "rm_monto",
            "slug": "rm_monto",
            "title": "RM_Monto",
            "type": "number"
          },
          {
            "columnType": "value",
            "conceptType": "value",
            "decimalChar": ".",
            "format": "default",
            "groupChar": "",
            "name": "de_monto",
            "slug": "de_monto",
            "title": "DE_Monto",
            "type": "number"
          },
          {
            "columnType": "value",
            "conceptType": "value",
            "decimalChar": ".",
            "format": "default",
            "groupChar": "",
            "name": "pa_monto",
            "slug": "pa_monto",
            "title": "PA_Monto",
            "type": "number"
          }
        ],
        "primaryKey": [
          "ejercicio",
          "titulo_codigo",
          "programa_codigo",
          "subprograma_codigo",
          "cog_partida_codigo",
          "cog_grupo_codigo",
          "cog_subpartida_codigo",
          "ce_partida_codigo",
          "ce_grupo_codigo",
          "ce_subpartida_codigo",
          "ce_renglon_codigo",
          "cf_clase_codigo",
          "cf_subclase_codigo",
          "cf_grupo_codigo",
          "cf_subgrupo_codigo",
          "ff_codigo"
        ]
      }
    }
  ],
  "revision": 0,
  "title": "Presupuesto de Egresos 2018 Costa Rica",
  "sample": [
    [
      "ejercicio",
      "mes",
      "titulo_codigo",
      "titulo_descripcion",
      "programa_codigo",
      "programa_descripcion",
      "subprograma_codigo",
      "subprograma_descripcion",
      "cog_partida_codigo",
      "cog_partida_descripcion",
      "cog_grupo_codigo",
      "cog_grupo_descripcion",
      "cog_subpartida_codigo",
      "cog_subpartida_descripcion",
      "ce_partida_codigo",
      "ce_partida_descripcion",
      "ce_grupo_codigo",
      "ce_grupo_descripcion",
      "ce_subpartida_codigo",
      "ce_subpartida_descripcion",
      "ce_renglon_codigo",
      "ce_renglon_descripcion",
      "cf_clase_codigo",
      "cf_clase_descripcion",
      "cf_subclase_codigo",
      "cf_subclase_descripcion",
      "cf_grupo_codigo",
      "cf_grupo_descripcion",
      "cf_subgrupo_codigo",
      "cf_subgrupo_descripcion",
      "ff_codigo",
      "ff_descripcion",
      "ff_clase1",
      "ff_clase2",
      "pi_monto",
      "pp_monto",
      "li_monto",
      "so_monto",
      "co_monto",
      "rm_monto",
      "de_monto",
      "pa_monto"
    ],
    [
      "2018",
      "01",
      "101",
      "Asamblea Legislativa",
      "002",
      "Asamblea Legislativa",
      "00",
      "",
      "0",
      "REMUNERACIONES",
      "001",
      "REMUNERACIONES BASICAS",
      "00101",
      "SUELDOS PARA CARGOS FIJOS",
      "1",
      "GASTOS CORRIENTES",
      "11",
      "GASTOS DE CONSUMO",
      "111",
      "REMUNERACIONES",
      "1111",
      "SUELDOS Y SALARIOS",
      "1",
      "FUNCIONES DE SERVICIOS PUBLICOS GENERALES",
      "11",
      "SERVICIOS PUBLICOS GENERALES",
      "112",
      "AYUDA ECONOMICA EXTERIOR",
      "1120",
      "AYUDA ECONOMICA EXTERIOR",
      "001",
      "Ingresos Corrientes",
      "Ingresos Corrientes",
      "INTERNO",
      "7611806243.00",
      "7611806243.00",
      "7611806243.00",
      "0.00",
      "842551.83",
      "0.00",
      "558587186.39",
      "558587186.39"
    ],
    [
      "2018",
      "02",
      "101",
      "Asamblea Legislativa",
      "002",
      "Asamblea Legislativa",
      "00",
      "",
      "0",
      "REMUNERACIONES",
      "001",
      "REMUNERACIONES BASICAS",
      "00101",
      "SUELDOS PARA CARGOS FIJOS",
      "1",
      "GASTOS CORRIENTES",
      "11",
      "GASTOS DE CONSUMO",
      "111",
      "REMUNERACIONES",
      "1111",
      "SUELDOS Y SALARIOS",
      "1",
      "FUNCIONES DE SERVICIOS PUBLICOS GENERALES",
      "11",
      "SERVICIOS PUBLICOS GENERALES",
      "112",
      "AYUDA ECONOMICA EXTERIOR",
      "1120",
      "AYUDA ECONOMICA EXTERIOR",
      "001",
      "Ingresos Corrientes",
      "Ingresos Corrientes",
      "INTERNO",
      "7611806243.00",
      "7611806243.00",
      "7611806243.00",
      "0.00",
      "842551.83",
      "0.00",
      "1113131248.36",
      "1113131248.36"
    ],
    [
      "2018",
      "03",
      "101",
      "Asamblea Legislativa",
      "002",
      "Asamblea Legislativa",
      "00",
      "",
      "0",
      "REMUNERACIONES",
      "001",
      "REMUNERACIONES BASICAS",
      "00101",
      "SUELDOS PARA CARGOS FIJOS",
      "1",
      "GASTOS CORRIENTES",
      "11",
      "GASTOS DE CONSUMO",
      "111",
      "REMUNERACIONES",
      "1111",
      "SUELDOS Y SALARIOS",
      "1",
      "FUNCIONES DE SERVICIOS PUBLICOS GENERALES",
      "11",
      "SERVICIOS PUBLICOS GENERALES",
      "112",
      "AYUDA ECONOMICA EXTERIOR",
      "1120",
      "AYUDA ECONOMICA EXTERIOR",
      "001",
      "Ingresos Corrientes",
      "Ingresos Corrientes",
      "INTERNO",
      "7611806243.00",
      "7611806243.00",
      "7611806243.00",
      "0.00",
      "842551.83",
      "0.00",
      "1710170557.10",
      "1710170557.10"
    ],
    [
      "2018",
      "04",
      "101",
      "Asamblea Legislativa",
      "002",
      "Asamblea Legislativa",
      "00",
      "",
      "0",
      "REMUNERACIONES",
      "001",
      "REMUNERACIONES BASICAS",
      "00101",
      "SUELDOS PARA CARGOS FIJOS",
      "1",
      "GASTOS CORRIENTES",
      "11",
      "GASTOS DE CONSUMO",
      "111",
      "REMUNERACIONES",
      "1111",
      "SUELDOS Y SALARIOS",
      "1",
      "FUNCIONES DE SERVICIOS PUBLICOS GENERALES",
      "11",
      "SERVICIOS PUBLICOS GENERALES",
      "112",
      "AYUDA ECONOMICA EXTERIOR",
      "1120",
      "AYUDA ECONOMICA EXTERIOR",
      "001",
      "Ingresos Corrientes",
      "Ingresos Corrientes",
      "INTERNO",
      "7611806243.00",
      "7611806243.00",
      "7611806243.00",
      "0.00",
      "842551.83",
      "0.00",
      "2288318257.88",
      "2288318257.88"
    ],
    [
      "2018",
      "05",
      "101",
      "Asamblea Legislativa",
      "002",
      "Asamblea Legislativa",
      "00",
      "",
      "0",
      "REMUNERACIONES",
      "001",
      "REMUNERACIONES BASICAS",
      "00101",
      "SUELDOS PARA CARGOS FIJOS",
      "1",
      "GASTOS CORRIENTES",
      "11",
      "GASTOS DE CONSUMO",
      "111",
      "REMUNERACIONES",
      "1111",
      "SUELDOS Y SALARIOS",
      "1",
      "FUNCIONES DE SERVICIOS PUBLICOS GENERALES",
      "11",
      "SERVICIOS PUBLICOS GENERALES",
      "112",
      "AYUDA ECONOMICA EXTERIOR",
      "1120",
      "AYUDA ECONOMICA EXTERIOR",
      "001",
      "Ingresos Corrientes",
      "Ingresos Corrientes",
      "INTERNO",
      "7611806243.00",
      "7611806243.00",
      "7611806243.00",
      "0.00",
      "842551.83",
      "0.00",
      "2802009392.48",
      "2802009392.48"
    ],
    [
      "2018",
      "06",
      "101",
      "Asamblea Legislativa",
      "002",
      "Asamblea Legislativa",
      "00",
      "",
      "0",
      "REMUNERACIONES",
      "001",
      "REMUNERACIONES BASICAS",
      "00101",
      "SUELDOS PARA CARGOS FIJOS",
      "1",
      "GASTOS CORRIENTES",
      "11",
      "GASTOS DE CONSUMO",
      "111",
      "REMUNERACIONES",
      "1111",
      "SUELDOS Y SALARIOS",
      "1",
      "FUNCIONES DE SERVICIOS PUBLICOS GENERALES",
      "11",
      "SERVICIOS PUBLICOS GENERALES",
      "112",
      "AYUDA ECONOMICA EXTERIOR",
      "1120",
      "AYUDA ECONOMICA EXTERIOR",
      "001",
      "Ingresos Corrientes",
      "Ingresos Corrientes",
      "INTERNO",
      "7611806243.00",
      "7611806243.00",
      "7611806243.00",
      "0.00",
      "842551.83",
      "0.00",
      "3418427563.12",
      "3418427563.12"
    ],
    [
      "2018",
      "07",
      "101",
      "Asamblea Legislativa",
      "002",
      "Asamblea Legislativa",
      "00",
      "",
      "0",
      "REMUNERACIONES",
      "001",
      "REMUNERACIONES BASICAS",
      "00101",
      "SUELDOS PARA CARGOS FIJOS",
      "1",
      "GASTOS CORRIENTES",
      "11",
      "GASTOS DE CONSUMO",
      "111",
      "REMUNERACIONES",
      "1111",
      "SUELDOS Y SALARIOS",
      "1",
      "FUNCIONES DE SERVICIOS PUBLICOS GENERALES",
      "11",
      "SERVICIOS PUBLICOS GENERALES",
      "112",
      "AYUDA ECONOMICA EXTERIOR",
      "1120",
      "AYUDA ECONOMICA EXTERIOR",
      "001",
      "Ingresos Corrientes",
      "Ingresos Corrientes",
      "INTERNO",
      "7611806243.00",
      "7611806243.00",
      "7611806243.00",
      "0.00",
      "842551.83",
      "0.00",
      "3997020241.19",
      "3997020241.19"
    ],
    [
      "2018",
      "08",
      "101",
      "Asamblea Legislativa",
      "002",
      "Asamblea Legislativa",
      "00",
      "",
      "0",
      "REMUNERACIONES",
      "001",
      "REMUNERACIONES BASICAS",
      "00101",
      "SUELDOS PARA CARGOS FIJOS",
      "1",
      "GASTOS CORRIENTES",
      "11",
      "GASTOS DE CONSUMO",
      "111",
      "REMUNERACIONES",
      "1111",
      "SUELDOS Y SALARIOS",
      "1",
      "FUNCIONES DE SERVICIOS PUBLICOS GENERALES",
      "11",
      "SERVICIOS PUBLICOS GENERALES",
      "112",
      "AYUDA ECONOMICA EXTERIOR",
      "1120",
      "AYUDA ECONOMICA EXTERIOR",
      "001",
      "Ingresos Corrientes",
      "Ingresos Corrientes",
      "INTERNO",
      "7611806243.00",
      "7611806243.00",
      "7611806243.00",
      "0.00",
      "842551.83",
      "0.00",
      "4570933465.36",
      "4570933465.36"
    ],
    [
      "2018",
      "09",
      "101",
      "Asamblea Legislativa",
      "002",
      "Asamblea Legislativa",
      "00",
      "",
      "0",
      "REMUNERACIONES",
      "001",
      "REMUNERACIONES BASICAS",
      "00101",
      "SUELDOS PARA CARGOS FIJOS",
      "1",
      "GASTOS CORRIENTES",
      "11",
      "GASTOS DE CONSUMO",
      "111",
      "REMUNERACIONES",
      "1111",
      "SUELDOS Y SALARIOS",
      "1",
      "FUNCIONES DE SERVICIOS PUBLICOS GENERALES",
      "11",
      "SERVICIOS PUBLICOS GENERALES",
      "112",
      "AYUDA ECONOMICA EXTERIOR",
      "1120",
      "AYUDA ECONOMICA EXTERIOR",
      "001",
      "Ingresos Corrientes",
      "Ingresos Corrientes",
      "INTERNO",
      "7611806243.00",
      "7611806243.00",
      "7611806243.00",
      "0.00",
      "842551.83",
      "0.00",
      "5158347253.73",
      "5158347253.73"
    ],
    [
      "2018",
      "10",
      "101",
      "Asamblea Legislativa",
      "002",
      "Asamblea Legislativa",
      "00",
      "",
      "0",
      "REMUNERACIONES",
      "001",
      "REMUNERACIONES BASICAS",
      "00101",
      "SUELDOS PARA CARGOS FIJOS",
      "1",
      "GASTOS CORRIENTES",
      "11",
      "GASTOS DE CONSUMO",
      "111",
      "REMUNERACIONES",
      "1111",
      "SUELDOS Y SALARIOS",
      "1",
      "FUNCIONES DE SERVICIOS PUBLICOS GENERALES",
      "11",
      "SERVICIOS PUBLICOS GENERALES",
      "112",
      "AYUDA ECONOMICA EXTERIOR",
      "1120",
      "AYUDA ECONOMICA EXTERIOR",
      "001",
      "Ingresos Corrientes",
      "Ingresos Corrientes",
      "INTERNO",
      "7611806243.00",
      "7611806243.00",
      "7611806243.00",
      "0.00",
      "842551.83",
      "0.00",
      "5735599899.77",
      "5735599899.77"
    ],
    [
      "2018",
      "11",
      "101",
      "Asamblea Legislativa",
      "002",
      "Asamblea Legislativa",
      "00",
      "",
      "0",
      "REMUNERACIONES",
      "001",
      "REMUNERACIONES BASICAS",
      "00101",
      "SUELDOS PARA CARGOS FIJOS",
      "1",
      "GASTOS CORRIENTES",
      "11",
      "GASTOS DE CONSUMO",
      "111",
      "REMUNERACIONES",
      "1111",
      "SUELDOS Y SALARIOS",
      "1",
      "FUNCIONES DE SERVICIOS PUBLICOS GENERALES",
      "11",
      "SERVICIOS PUBLICOS GENERALES",
      "112",
      "AYUDA ECONOMICA EXTERIOR",
      "1120",
      "AYUDA ECONOMICA EXTERIOR",
      "001",
      "Ingresos Corrientes",
      "Ingresos Corrientes",
      "INTERNO",
      "7611806243.00",
      "7561806243.00",
      "7561806243.00",
      "0.00",
      "289700146.63",
      "0.00",
      "6310278003.75",
      "6310278003.75"
    ],
    [
      "2018",
      "12",
      "101",
      "Asamblea Legislativa",
      "002",
      "Asamblea Legislativa",
      "00",
      "",
      "0",
      "REMUNERACIONES",
      "001",
      "REMUNERACIONES BASICAS",
      "00101",
      "SUELDOS PARA CARGOS FIJOS",
      "1",
      "GASTOS CORRIENTES",
      "11",
      "GASTOS DE CONSUMO",
      "111",
      "REMUNERACIONES",
      "1111",
      "SUELDOS Y SALARIOS",
      "1",
      "FUNCIONES DE SERVICIOS PUBLICOS GENERALES",
      "11",
      "SERVICIOS PUBLICOS GENERALES",
      "112",
      "AYUDA ECONOMICA EXTERIOR",
      "1120",
      "AYUDA ECONOMICA EXTERIOR",
      "001",
      "Ingresos Corrientes",
      "Ingresos Corrientes",
      "INTERNO",
      "7611806243.00",
      "7561806243.00",
      "7561806243.00",
      "0.00",
      "0.00",
      "0.00",
      "6874736053.05",
      "6874736053.05"
    ],
    [
      "2018",
      "01",
      "101",
      "Asamblea Legislativa",
      "002",
      "Asamblea Legislativa",
      "00",
      "",
      "0",
      "REMUNERACIONES",
      "001",
      "REMUNERACIONES BASICAS",
      "00105",
      "SUPLENCIAS",
      "1",
      "GASTOS CORRIENTES",
      "11",
      "GASTOS DE CONSUMO",
      "111",
      "REMUNERACIONES",
      "1111",
      "SUELDOS Y SALARIOS",
      "1",
      "FUNCIONES DE SERVICIOS PUBLICOS GENERALES",
      "11",
      "SERVICIOS PUBLICOS GENERALES",
      "112",
      "AYUDA ECONOMICA EXTERIOR",
      "1120",
      "AYUDA ECONOMICA EXTERIOR",
      "001",
      "Ingresos Corrientes",
      "Ingresos Corrientes",
      "INTERNO",
      "160000000.00",
      "160000000.00",
      "160000000.00",
      "0.00",
      "0.00",
      "0.00",
      "10171450.78",
      "10171450.78"
    ],
    [
      "2018",
      "02",
      "101",
      "Asamblea Legislativa",
      "002",
      "Asamblea Legislativa",
      "00",
      "",
      "0",
      "REMUNERACIONES",
      "001",
      "REMUNERACIONES BASICAS",
      "00105",
      "SUPLENCIAS",
      "1",
      "GASTOS CORRIENTES",
      "11",
      "GASTOS DE CONSUMO",
      "111",
      "REMUNERACIONES",
      "1111",
      "SUELDOS Y SALARIOS",
      "1",
      "FUNCIONES DE SERVICIOS PUBLICOS GENERALES",
      "11",
      "SERVICIOS PUBLICOS GENERALES",
      "112",
      "AYUDA ECONOMICA EXTERIOR",
      "1120",
      "AYUDA ECONOMICA EXTERIOR",
      "001",
      "Ingresos Corrientes",
      "Ingresos Corrientes",
      "INTERNO",
      "160000000.00",
      "160000000.00",
      "160000000.00",
      "0.00",
      "0.00",
      "0.00",
      "22343538.23",
      "22343538.23"
    ],
    [
      "2018",
      "03",
      "101",
      "Asamblea Legislativa",
      "002",
      "Asamblea Legislativa",
      "00",
      "",
      "0",
      "REMUNERACIONES",
      "001",
      "REMUNERACIONES BASICAS",
      "00105",
      "SUPLENCIAS",
      "1",
      "GASTOS CORRIENTES",
      "11",
      "GASTOS DE CONSUMO",
      "111",
      "REMUNERACIONES",
      "1111",
      "SUELDOS Y SALARIOS",
      "1",
      "FUNCIONES DE SERVICIOS PUBLICOS GENERALES",
      "11",
      "SERVICIOS PUBLICOS GENERALES",
      "112",
      "AYUDA ECONOMICA EXTERIOR",
      "1120",
      "AYUDA ECONOMICA EXTERIOR",
      "001",
      "Ingresos Corrientes",
      "Ingresos Corrientes",
      "INTERNO",
      "160000000.00",
      "160000000.00",
      "160000000.00",
      "0.00",
      "0.00",
      "0.00",
      "30954564.94",
      "30954564.94"
    ],
    [
      "2018",
      "04",
      "101",
      "Asamblea Legislativa",
      "002",
      "Asamblea Legislativa",
      "00",
      "",
      "0",
      "REMUNERACIONES",
      "001",
      "REMUNERACIONES BASICAS",
      "00105",
      "SUPLENCIAS",
      "1",
      "GASTOS CORRIENTES",
      "11",
      "GASTOS DE CONSUMO",
      "111",
      "REMUNERACIONES",
      "1111",
      "SUELDOS Y SALARIOS",
      "1",
      "FUNCIONES DE SERVICIOS PUBLICOS GENERALES",
      "11",
      "SERVICIOS PUBLICOS GENERALES",
      "112",
      "AYUDA ECONOMICA EXTERIOR",
      "1120",
      "AYUDA ECONOMICA EXTERIOR",
      "001",
      "Ingresos Corrientes",
      "Ingresos Corrientes",
      "INTERNO",
      "160000000.00",
      "160000000.00",
      "160000000.00",
      "0.00",
      "0.00",
      "0.00",
      "37891485.63",
      "37891485.63"
    ],
    [
      "2018",
      "05",
      "101",
      "Asamblea Legislativa",
      "002",
      "Asamblea Legislativa",
      "00",
      "",
      "0",
      "REMUNERACIONES",
      "001",
      "REMUNERACIONES BASICAS",
      "00105",
      "SUPLENCIAS",
      "1",
      "GASTOS CORRIENTES",
      "11",
      "GASTOS DE CONSUMO",
      "111",
      "REMUNERACIONES",
      "1111",
      "SUELDOS Y SALARIOS",
      "1",
      "FUNCIONES DE SERVICIOS PUBLICOS GENERALES",
      "11",
      "SERVICIOS PUBLICOS GENERALES",
      "112",
      "AYUDA ECONOMICA EXTERIOR",
      "1120",
      "AYUDA ECONOMICA EXTERIOR",
      "001",
      "Ingresos Corrientes",
      "Ingresos Corrientes",
      "INTERNO",
      "160000000.00",
      "160000000.00",
      "160000000.00",
      "0.00",
      "0.00",
      "0.00",
      "44376135.68",
      "44376135.68"
    ],
    [
      "2018",
      "06",
      "101",
      "Asamblea Legislativa",
      "002",
      "Asamblea Legislativa",
      "00",
      "",
      "0",
      "REMUNERACIONES",
      "001",
      "REMUNERACIONES BASICAS",
      "00105",
      "SUPLENCIAS",
      "1",
      "GASTOS CORRIENTES",
      "11",
      "GASTOS DE CONSUMO",
      "111",
      "REMUNERACIONES",
      "1111",
      "SUELDOS Y SALARIOS",
      "1",
      "FUNCIONES DE SERVICIOS PUBLICOS GENERALES",
      "11",
      "SERVICIOS PUBLICOS GENERALES",
      "112",
      "AYUDA ECONOMICA EXTERIOR",
      "1120",
      "AYUDA ECONOMICA EXTERIOR",
      "001",
      "Ingresos Corrientes",
      "Ingresos Corrientes",
      "INTERNO",
      "160000000.00",
      "160000000.00",
      "160000000.00",
      "0.00",
      "0.00",
      "0.00",
      "50638229.85",
      "50638229.85"
    ],
    [
      "2018",
      "07",
      "101",
      "Asamblea Legislativa",
      "002",
      "Asamblea Legislativa",
      "00",
      "",
      "0",
      "REMUNERACIONES",
      "001",
      "REMUNERACIONES BASICAS",
      "00105",
      "SUPLENCIAS",
      "1",
      "GASTOS CORRIENTES",
      "11",
      "GASTOS DE CONSUMO",
      "111",
      "REMUNERACIONES",
      "1111",
      "SUELDOS Y SALARIOS",
      "1",
      "FUNCIONES DE SERVICIOS PUBLICOS GENERALES",
      "11",
      "SERVICIOS PUBLICOS GENERALES",
      "112",
      "AYUDA ECONOMICA EXTERIOR",
      "1120",
      "AYUDA ECONOMICA EXTERIOR",
      "001",
      "Ingresos Corrientes",
      "Ingresos Corrientes",
      "INTERNO",
      "160000000.00",
      "160000000.00",
      "160000000.00",
      "0.00",
      "0.00",
      "0.00",
      "55594799.46",
      "55594799.46"
    ],
    [
      "2018",
      "08",
      "101",
      "Asamblea Legislativa",
      "002",
      "Asamblea Legislativa",
      "00",
      "",
      "0",
      "REMUNERACIONES",
      "001",
      "REMUNERACIONES BASICAS",
      "00105",
      "SUPLENCIAS",
      "1",
      "GASTOS CORRIENTES",
      "11",
      "GASTOS DE CONSUMO",
      "111",
      "REMUNERACIONES",
      "1111",
      "SUELDOS Y SALARIOS",
      "1",
      "FUNCIONES DE SERVICIOS PUBLICOS GENERALES",
      "11",
      "SERVICIOS PUBLICOS GENERALES",
      "112",
      "AYUDA ECONOMICA EXTERIOR",
      "1120",
      "AYUDA ECONOMICA EXTERIOR",
      "001",
      "Ingresos Corrientes",
      "Ingresos Corrientes",
      "INTERNO",
      "160000000.00",
      "160000000.00",
      "160000000.00",
      "0.00",
      "0.00",
      "0.00",
      "62609439.14",
      "62609439.14"
    ],
    [
      "2018",
      "09",
      "101",
      "Asamblea Legislativa",
      "002",
      "Asamblea Legislativa",
      "00",
      "",
      "0",
      "REMUNERACIONES",
      "001",
      "REMUNERACIONES BASICAS",
      "00105",
      "SUPLENCIAS",
      "1",
      "GASTOS CORRIENTES",
      "11",
      "GASTOS DE CONSUMO",
      "111",
      "REMUNERACIONES",
      "1111",
      "SUELDOS Y SALARIOS",
      "1",
      "FUNCIONES DE SERVICIOS PUBLICOS GENERALES",
      "11",
      "SERVICIOS PUBLICOS GENERALES",
      "112",
      "AYUDA ECONOMICA EXTERIOR",
      "1120",
      "AYUDA ECONOMICA EXTERIOR",
      "001",
      "Ingresos Corrientes",
      "Ingresos Corrientes",
      "INTERNO",
      "160000000.00",
      "160000000.00",
      "160000000.00",
      "0.00",
      "0.00",
      "0.00",
      "70802369.59",
      "70802369.59"
    ],
    [
      "2018",
      "10",
      "101",
      "Asamblea Legislativa",
      "002",
      "Asamblea Legislativa",
      "00",
      "",
      "0",
      "REMUNERACIONES",
      "001",
      "REMUNERACIONES BASICAS",
      "00105",
      "SUPLENCIAS",
      "1",
      "GASTOS CORRIENTES",
      "11",
      "GASTOS DE CONSUMO",
      "111",
      "REMUNERACIONES",
      "1111",
      "SUELDOS Y SALARIOS",
      "1",
      "FUNCIONES DE SERVICIOS PUBLICOS GENERALES",
      "11",
      "SERVICIOS PUBLICOS GENERALES",
      "112",
      "AYUDA ECONOMICA EXTERIOR",
      "1120",
      "AYUDA ECONOMICA EXTERIOR",
      "001",
      "Ingresos Corrientes",
      "Ingresos Corrientes",
      "INTERNO",
      "160000000.00",
      "160000000.00",
      "160000000.00",
      "0.00",
      "0.00",
      "0.00",
      "76966313.98",
      "76966313.98"
    ],
    [
      "2018",
      "11",
      "101",
      "Asamblea Legislativa",
      "002",
      "Asamblea Legislativa",
      "00",
      "",
      "0",
      "REMUNERACIONES",
      "001",
      "REMUNERACIONES BASICAS",
      "00105",
      "SUPLENCIAS",
      "1",
      "GASTOS CORRIENTES",
      "11",
      "GASTOS DE CONSUMO",
      "111",
      "REMUNERACIONES",
      "1111",
      "SUELDOS Y SALARIOS",
      "1",
      "FUNCIONES DE SERVICIOS PUBLICOS GENERALES",
      "11",
      "SERVICIOS PUBLICOS GENERALES",
      "112",
      "AYUDA ECONOMICA EXTERIOR",
      "1120",
      "AYUDA ECONOMICA EXTERIOR",
      "001",
      "Ingresos Corrientes",
      "Ingresos Corrientes",
      "INTERNO",
      "160000000.00",
      "160000000.00",
      "160000000.00",
      "0.00",
      "0.00",
      "0.00",
      "83438588.52",
      "83438588.52"
    ],
    [
      "2018",
      "12",
      "101",
      "Asamblea Legislativa",
      "002",
      "Asamblea Legislativa",
      "00",
      "",
      "0",
      "REMUNERACIONES",
      "001",
      "REMUNERACIONES BASICAS",
      "00105",
      "SUPLENCIAS",
      "1",
      "GASTOS CORRIENTES",
      "11",
      "GASTOS DE CONSUMO",
      "111",
      "REMUNERACIONES",
      "1111",
      "SUELDOS Y SALARIOS",
      "1",
      "FUNCIONES DE SERVICIOS PUBLICOS GENERALES",
      "11",
      "SERVICIOS PUBLICOS GENERALES",
      "112",
      "AYUDA ECONOMICA EXTERIOR",
      "1120",
      "AYUDA ECONOMICA EXTERIOR",
      "001",
      "Ingresos Corrientes",
      "Ingresos Corrientes",
      "INTERNO",
      "160000000.00",
      "160000000.00",
      "160000000.00",
      "0.00",
      "0.00",
      "0.00",
      "90070044.53",
      "90070044.53"
    ],
    [
      "2018",
      "01",
      "101",
      "Asamblea Legislativa",
      "002",
      "Asamblea Legislativa",
      "00",
      "",
      "0",
      "REMUNERACIONES",
      "002",
      "REMUNERACIONES EVENTUALES",
      "00201",
      "TIEMPO EXTRAORDINARIO",
      "1",
      "GASTOS CORRIENTES",
      "11",
      "GASTOS DE CONSUMO",
      "111",
      "REMUNERACIONES",
      "1111",
      "SUELDOS Y SALARIOS",
      "1",
      "FUNCIONES DE SERVICIOS PUBLICOS GENERALES",
      "11",
      "SERVICIOS PUBLICOS GENERALES",
      "112",
      "AYUDA ECONOMICA EXTERIOR",
      "1120",
      "AYUDA ECONOMICA EXTERIOR",
      "001",
      "Ingresos Corrientes",
      "Ingresos Corrientes",
      "INTERNO",
      "300000000.00",
      "300000000.00",
      "300000000.00",
      "0.00",
      "0.00",
      "0.00",
      "36880284.90",
      "36880284.90"
    ],
    [
      "2018",
      "02",
      "101",
      "Asamblea Legislativa",
      "002",
      "Asamblea Legislativa",
      "00",
      "",
      "0",
      "REMUNERACIONES",
      "002",
      "REMUNERACIONES EVENTUALES",
      "00201",
      "TIEMPO EXTRAORDINARIO",
      "1",
      "GASTOS CORRIENTES",
      "11",
      "GASTOS DE CONSUMO",
      "111",
      "REMUNERACIONES",
      "1111",
      "SUELDOS Y SALARIOS",
      "1",
      "FUNCIONES DE SERVICIOS PUBLICOS GENERALES",
      "11",
      "SERVICIOS PUBLICOS GENERALES",
      "112",
      "AYUDA ECONOMICA EXTERIOR",
      "1120",
      "AYUDA ECONOMICA EXTERIOR",
      "001",
      "Ingresos Corrientes",
      "Ingresos Corrientes",
      "INTERNO",
      "300000000.00",
      "300000000.00",
      "300000000.00",
      "0.00",
      "0.00",
      "0.00",
      "59465804.16",
      "59465804.16"
    ],
    [
      "2018",
      "03",
      "101",
      "Asamblea Legislativa",
      "002",
      "Asamblea Legislativa",
      "00",
      "",
      "0",
      "REMUNERACIONES",
      "002",
      "REMUNERACIONES EVENTUALES",
      "00201",
      "TIEMPO EXTRAORDINARIO",
      "1",
      "GASTOS CORRIENTES",
      "11",
      "GASTOS DE CONSUMO",
      "111",
      "REMUNERACIONES",
      "1111",
      "SUELDOS Y SALARIOS",
      "1",
      "FUNCIONES DE SERVICIOS PUBLICOS GENERALES",
      "11",
      "SERVICIOS PUBLICOS GENERALES",
      "112",
      "AYUDA ECONOMICA EXTERIOR",
      "1120",
      "AYUDA ECONOMICA EXTERIOR",
      "001",
      "Ingresos Corrientes",
      "Ingresos Corrientes",
      "INTERNO",
      "300000000.00",
      "300000000.00",
      "300000000.00",
      "0.00",
      "0.00",
      "0.00",
      "78630672.31",
      "78630672.31"
    ],
    [
      "2018",
      "04",
      "101",
      "Asamblea Legislativa",
      "002",
      "Asamblea Legislativa",
      "00",
      "",
      "0",
      "REMUNERACIONES",
      "002",
      "REMUNERACIONES EVENTUALES",
      "00201",
      "TIEMPO EXTRAORDINARIO",
      "1",
      "GASTOS CORRIENTES",
      "11",
      "GASTOS DE CONSUMO",
      "111",
      "REMUNERACIONES",
      "1111",
      "SUELDOS Y SALARIOS",
      "1",
      "FUNCIONES DE SERVICIOS PUBLICOS GENERALES",
      "11",
      "SERVICIOS PUBLICOS GENERALES",
      "112",
      "AYUDA ECONOMICA EXTERIOR",
      "1120",
      "AYUDA ECONOMICA EXTERIOR",
      "001",
      "Ingresos Corrientes",
      "Ingresos Corrientes",
      "INTERNO",
      "300000000.00",
      "300000000.00",
      "300000000.00",
      "0.00",
      "0.00",
      "0.00",
      "102026706.04",
      "102026706.04"
    ],
    [
      "2018",
      "05",
      "101",
      "Asamblea Legislativa",
      "002",
      "Asamblea Legislativa",
      "00",
      "",
      "0",
      "REMUNERACIONES",
      "002",
      "REMUNERACIONES EVENTUALES",
      "00201",
      "TIEMPO EXTRAORDINARIO",
      "1",
      "GASTOS CORRIENTES",
      "11",
      "GASTOS DE CONSUMO",
      "111",
      "REMUNERACIONES",
      "1111",
      "SUELDOS Y SALARIOS",
      "1",
      "FUNCIONES DE SERVICIOS PUBLICOS GENERALES",
      "11",
      "SERVICIOS PUBLICOS GENERALES",
      "112",
      "AYUDA ECONOMICA EXTERIOR",
      "1120",
      "AYUDA ECONOMICA EXTERIOR",
      "001",
      "Ingresos Corrientes",
      "Ingresos Corrientes",
      "INTERNO",
      "300000000.00",
      "300000000.00",
      "300000000.00",
      "0.00",
      "0.00",
      "0.00",
      "133663499.83",
      "133663499.83"
    ],
    [
      "2018",
      "06",
      "101",
      "Asamblea Legislativa",
      "002",
      "Asamblea Legislativa",
      "00",
      "",
      "0",
      "REMUNERACIONES",
      "002",
      "REMUNERACIONES EVENTUALES",
      "00201",
      "TIEMPO EXTRAORDINARIO",
      "1",
      "GASTOS CORRIENTES",
      "11",
      "GASTOS DE CONSUMO",
      "111",
      "REMUNERACIONES",
      "1111",
      "SUELDOS Y SALARIOS",
      "1",
      "FUNCIONES DE SERVICIOS PUBLICOS GENERALES",
      "11",
      "SERVICIOS PUBLICOS GENERALES",
      "112",
      "AYUDA ECONOMICA EXTERIOR",
      "1120",
      "AYUDA ECONOMICA EXTERIOR",
      "001",
      "Ingresos Corrientes",
      "Ingresos Corrientes",
      "INTERNO",
      "300000000.00",
      "300000000.00",
      "300000000.00",
      "0.00",
      "0.00",
      "0.00",
      "171460284.17",
      "171460284.17"
    ],
    [
      "2018",
      "07",
      "101",
      "Asamblea Legislativa",
      "002",
      "Asamblea Legislativa",
      "00",
      "",
      "0",
      "REMUNERACIONES",
      "002",
      "REMUNERACIONES EVENTUALES",
      "00201",
      "TIEMPO EXTRAORDINARIO",
      "1",
      "GASTOS CORRIENTES",
      "11",
      "GASTOS DE CONSUMO",
      "111",
      "REMUNERACIONES",
      "1111",
      "SUELDOS Y SALARIOS",
      "1",
      "FUNCIONES DE SERVICIOS PUBLICOS GENERALES",
      "11",
      "SERVICIOS PUBLICOS GENERALES",
      "112",
      "AYUDA ECONOMICA EXTERIOR",
      "1120",
      "AYUDA ECONOMICA EXTERIOR",
      "001",
      "Ingresos Corrientes",
      "Ingresos Corrientes",
      "INTERNO",
      "300000000.00",
      "300000000.00",
      "300000000.00",
      "0.00",
      "0.00",
      "0.00",
      "200910406.80",
      "200910406.80"
    ],
    [
      "2018",
      "08",
      "101",
      "Asamblea Legislativa",
      "002",
      "Asamblea Legislativa",
      "00",
      "",
      "0",
      "REMUNERACIONES",
      "002",
      "REMUNERACIONES EVENTUALES",
      "00201",
      "TIEMPO EXTRAORDINARIO",
      "1",
      "GASTOS CORRIENTES",
      "11",
      "GASTOS DE CONSUMO",
      "111",
      "REMUNERACIONES",
      "1111",
      "SUELDOS Y SALARIOS",
      "1",
      "FUNCIONES DE SERVICIOS PUBLICOS GENERALES",
      "11",
      "SERVICIOS PUBLICOS GENERALES",
      "112",
      "AYUDA ECONOMICA EXTERIOR",
      "1120",
      "AYUDA ECONOMICA EXTERIOR",
      "001",
      "Ingresos Corrientes",
      "Ingresos Corrientes",
      "INTERNO",
      "300000000.00",
      "300000000.00",
      "300000000.00",
      "0.00",
      "0.00",
      "0.00",
      "223351802.32",
      "223351802.32"
    ],
    [
      "2018",
      "09",
      "101",
      "Asamblea Legislativa",
      "002",
      "Asamblea Legislativa",
      "00",
      "",
      "0",
      "REMUNERACIONES",
      "002",
      "REMUNERACIONES EVENTUALES",
      "00201",
      "TIEMPO EXTRAORDINARIO",
      "1",
      "GASTOS CORRIENTES",
      "11",
      "GASTOS DE CONSUMO",
      "111",
      "REMUNERACIONES",
      "1111",
      "SUELDOS Y SALARIOS",
      "1",
      "FUNCIONES DE SERVICIOS PUBLICOS GENERALES",
      "11",
      "SERVICIOS PUBLICOS GENERALES",
      "112",
      "AYUDA ECONOMICA EXTERIOR",
      "1120",
      "AYUDA ECONOMICA EXTERIOR",
      "001",
      "Ingresos Corrientes",
      "Ingresos Corrientes",
      "INTERNO",
      "300000000.00",
      "300000000.00",
      "300000000.00",
      "0.00",
      "0.00",
      "0.00",
      "245508541.82",
      "245508541.82"
    ],
    [
      "2018",
      "10",
      "101",
      "Asamblea Legislativa",
      "002",
      "Asamblea Legislativa",
      "00",
      "",
      "0",
      "REMUNERACIONES",
      "002",
      "REMUNERACIONES EVENTUALES",
      "00201",
      "TIEMPO EXTRAORDINARIO",
      "1",
      "GASTOS CORRIENTES",
      "11",
      "GASTOS DE CONSUMO",
      "111",
      "REMUNERACIONES",
      "1111",
      "SUELDOS Y SALARIOS",
      "1",
      "FUNCIONES DE SERVICIOS PUBLICOS GENERALES",
      "11",
      "SERVICIOS PUBLICOS GENERALES",
      "112",
      "AYUDA ECONOMICA EXTERIOR",
      "1120",
      "AYUDA ECONOMICA EXTERIOR",
      "001",
      "Ingresos Corrientes",
      "Ingresos Corrientes",
      "INTERNO",
      "300000000.00",
      "300000000.00",
      "300000000.00",
      "0.00",
      "0.00",
      "0.00",
      "270108436.52",
      "270108436.52"
    ],
    [
      "2018",
      "11",
      "101",
      "Asamblea Legislativa",
      "002",
      "Asamblea Legislativa",
      "00",
      "",
      "0",
      "REMUNERACIONES",
      "002",
      "REMUNERACIONES EVENTUALES",
      "00201",
      "TIEMPO EXTRAORDINARIO",
      "1",
      "GASTOS CORRIENTES",
      "11",
      "GASTOS DE CONSUMO",
      "111",
      "REMUNERACIONES",
      "1111",
      "SUELDOS Y SALARIOS",
      "1",
      "FUNCIONES DE SERVICIOS PUBLICOS GENERALES",
      "11",
      "SERVICIOS PUBLICOS GENERALES",
      "112",
      "AYUDA ECONOMICA EXTERIOR",
      "1120",
      "AYUDA ECONOMICA EXTERIOR",
      "001",
      "Ingresos Corrientes",
      "Ingresos Corrientes",
      "INTERNO",
      "300000000.00",
      "350000000.00",
      "350000000.00",
      "0.00",
      "0.00",
      "0.00",
      "309905905.71",
      "309905905.71"
    ],
    [
      "2018",
      "12",
      "101",
      "Asamblea Legislativa",
      "002",
      "Asamblea Legislativa",
      "00",
      "",
      "0",
      "REMUNERACIONES",
      "002",
      "REMUNERACIONES EVENTUALES",
      "00201",
      "TIEMPO EXTRAORDINARIO",
      "1",
      "GASTOS CORRIENTES",
      "11",
      "GASTOS DE CONSUMO",
      "111",
      "REMUNERACIONES",
      "1111",
      "SUELDOS Y SALARIOS",
      "1",
      "FUNCIONES DE SERVICIOS PUBLICOS GENERALES",
      "11",
      "SERVICIOS PUBLICOS GENERALES",
      "112",
      "AYUDA ECONOMICA EXTERIOR",
      "1120",
      "AYUDA ECONOMICA EXTERIOR",
      "001",
      "Ingresos Corrientes",
      "Ingresos Corrientes",
      "INTERNO",
      "300000000.00",
      "350000000.00",
      "350000000.00",
      "0.00",
      "0.00",
      "0.00",
      "349680189.84",
      "349680189.84"
    ],
    [
      "2018",
      "01",
      "101",
      "Asamblea Legislativa",
      "002",
      "Asamblea Legislativa",
      "00",
      "",
      "0",
      "REMUNERACIONES",
      "002",
      "REMUNERACIONES EVENTUALES",
      "00202",
      "RECARGO DE FUNCIONES",
      "1",
      "GASTOS CORRIENTES",
      "11",
      "GASTOS DE CONSUMO",
      "111",
      "REMUNERACIONES",
      "1111",
      "SUELDOS Y SALARIOS",
      "1",
      "FUNCIONES DE SERVICIOS PUBLICOS GENERALES",
      "11",
      "SERVICIOS PUBLICOS GENERALES",
      "112",
      "AYUDA ECONOMICA EXTERIOR",
      "1120",
      "AYUDA ECONOMICA EXTERIOR",
      "001",
      "Ingresos Corrientes",
      "Ingresos Corrientes",
      "INTERNO",
      "10000000.00",
      "10000000.00",
      "10000000.00",
      "0.00",
      "0.00",
      "0.00",
      "0.00",
      "0.00"
    ],
    [
      "2018",
      "02",
      "101",
      "Asamblea Legislativa",
      "002",
      "Asamblea Legislativa",
      "00",
      "",
      "0",
      "REMUNERACIONES",
      "002",
      "REMUNERACIONES EVENTUALES",
      "00202",
      "RECARGO DE FUNCIONES",
      "1",
      "GASTOS CORRIENTES",
      "11",
      "GASTOS DE CONSUMO",
      "111",
      "REMUNERACIONES",
      "1111",
      "SUELDOS Y SALARIOS",
      "1",
      "FUNCIONES DE SERVICIOS PUBLICOS GENERALES",
      "11",
      "SERVICIOS PUBLICOS GENERALES",
      "112",
      "AYUDA ECONOMICA EXTERIOR",
      "1120",
      "AYUDA ECONOMICA EXTERIOR",
      "001",
      "Ingresos Corrientes",
      "Ingresos Corrientes",
      "INTERNO",
      "10000000.00",
      "10000000.00",
      "10000000.00",
      "0.00",
      "0.00",
      "0.00",
      "0.00",
      "0.00"
    ],
    [
      "2018",
      "03",
      "101",
      "Asamblea Legislativa",
      "002",
      "Asamblea Legislativa",
      "00",
      "",
      "0",
      "REMUNERACIONES",
      "002",
      "REMUNERACIONES EVENTUALES",
      "00202",
      "RECARGO DE FUNCIONES",
      "1",
      "GASTOS CORRIENTES",
      "11",
      "GASTOS DE CONSUMO",
      "111",
      "REMUNERACIONES",
      "1111",
      "SUELDOS Y SALARIOS",
      "1",
      "FUNCIONES DE SERVICIOS PUBLICOS GENERALES",
      "11",
      "SERVICIOS PUBLICOS GENERALES",
      "112",
      "AYUDA ECONOMICA EXTERIOR",
      "1120",
      "AYUDA ECONOMICA EXTERIOR",
      "001",
      "Ingresos Corrientes",
      "Ingresos Corrientes",
      "INTERNO",
      "10000000.00",
      "10000000.00",
      "10000000.00",
      "0.00",
      "0.00",
      "0.00",
      "0.00",
      "0.00"
    ],
    [
      "2018",
      "04",
      "101",
      "Asamblea Legislativa",
      "002",
      "Asamblea Legislativa",
      "00",
      "",
      "0",
      "REMUNERACIONES",
      "002",
      "REMUNERACIONES EVENTUALES",
      "00202",
      "RECARGO DE FUNCIONES",
      "1",
      "GASTOS CORRIENTES",
      "11",
      "GASTOS DE CONSUMO",
      "111",
      "REMUNERACIONES",
      "1111",
      "SUELDOS Y SALARIOS",
      "1",
      "FUNCIONES DE SERVICIOS PUBLICOS GENERALES",
      "11",
      "SERVICIOS PUBLICOS GENERALES",
      "112",
      "AYUDA ECONOMICA EXTERIOR",
      "1120",
      "AYUDA ECONOMICA EXTERIOR",
      "001",
      "Ingresos Corrientes",
      "Ingresos Corrientes",
      "INTERNO",
      "10000000.00",
      "10000000.00",
      "10000000.00",
      "0.00",
      "0.00",
      "0.00",
      "0.00",
      "0.00"
    ],
    [
      "2018",
      "05",
      "101",
      "Asamblea Legislativa",
      "002",
      "Asamblea Legislativa",
      "00",
      "",
      "0",
      "REMUNERACIONES",
      "002",
      "REMUNERACIONES EVENTUALES",
      "00202",
      "RECARGO DE FUNCIONES",
      "1",
      "GASTOS CORRIENTES",
      "11",
      "GASTOS DE CONSUMO",
      "111",
      "REMUNERACIONES",
      "1111",
      "SUELDOS Y SALARIOS",
      "1",
      "FUNCIONES DE SERVICIOS PUBLICOS GENERALES",
      "11",
      "SERVICIOS PUBLICOS GENERALES",
      "112",
      "AYUDA ECONOMICA EXTERIOR",
      "1120",
      "AYUDA ECONOMICA EXTERIOR",
      "001",
      "Ingresos Corrientes",
      "Ingresos Corrientes",
      "INTERNO",
      "10000000.00",
      "10000000.00",
      "10000000.00",
      "0.00",
      "0.00",
      "0.00",
      "0.00",
      "0.00"
    ],
    [
      "2018",
      "06",
      "101",
      "Asamblea Legislativa",
      "002",
      "Asamblea Legislativa",
      "00",
      "",
      "0",
      "REMUNERACIONES",
      "002",
      "REMUNERACIONES EVENTUALES",
      "00202",
      "RECARGO DE FUNCIONES",
      "1",
      "GASTOS CORRIENTES",
      "11",
      "GASTOS DE CONSUMO",
      "111",
      "REMUNERACIONES",
      "1111",
      "SUELDOS Y SALARIOS",
      "1",
      "FUNCIONES DE SERVICIOS PUBLICOS GENERALES",
      "11",
      "SERVICIOS PUBLICOS GENERALES",
      "112",
      "AYUDA ECONOMICA EXTERIOR",
      "1120",
      "AYUDA ECONOMICA EXTERIOR",
      "001",
      "Ingresos Corrientes",
      "Ingresos Corrientes",
      "INTERNO",
      "10000000.00",
      "10000000.00",
      "10000000.00",
      "0.00",
      "0.00",
      "0.00",
      "0.00",
      "0.00"
    ],
    [
      "2018",
      "07",
      "101",
      "Asamblea Legislativa",
      "002",
      "Asamblea Legislativa",
      "00",
      "",
      "0",
      "REMUNERACIONES",
      "002",
      "REMUNERACIONES EVENTUALES",
      "00202",
      "RECARGO DE FUNCIONES",
      "1",
      "GASTOS CORRIENTES",
      "11",
      "GASTOS DE CONSUMO",
      "111",
      "REMUNERACIONES",
      "1111",
      "SUELDOS Y SALARIOS",
      "1",
      "FUNCIONES DE SERVICIOS PUBLICOS GENERALES",
      "11",
      "SERVICIOS PUBLICOS GENERALES",
      "112",
      "AYUDA ECONOMICA EXTERIOR",
      "1120",
      "AYUDA ECONOMICA EXTERIOR",
      "001",
      "Ingresos Corrientes",
      "Ingresos Corrientes",
      "INTERNO",
      "10000000.00",
      "10000000.00",
      "10000000.00",
      "0.00",
      "0.00",
      "0.00",
      "0.00",
      "0.00"
    ],
    [
      "2018",
      "08",
      "101",
      "Asamblea Legislativa",
      "002",
      "Asamblea Legislativa",
      "00",
      "",
      "0",
      "REMUNERACIONES",
      "002",
      "REMUNERACIONES EVENTUALES",
      "00202",
      "RECARGO DE FUNCIONES",
      "1",
      "GASTOS CORRIENTES",
      "11",
      "GASTOS DE CONSUMO",
      "111",
      "REMUNERACIONES",
      "1111",
      "SUELDOS Y SALARIOS",
      "1",
      "FUNCIONES DE SERVICIOS PUBLICOS GENERALES",
      "11",
      "SERVICIOS PUBLICOS GENERALES",
      "112",
      "AYUDA ECONOMICA EXTERIOR",
      "1120",
      "AYUDA ECONOMICA EXTERIOR",
      "001",
      "Ingresos Corrientes",
      "Ingresos Corrientes",
      "INTERNO",
      "10000000.00",
      "10000000.00",
      "10000000.00",
      "0.00",
      "0.00",
      "0.00",
      "0.00",
      "0.00"
    ],
    [
      "2018",
      "09",
      "101",
      "Asamblea Legislativa",
      "002",
      "Asamblea Legislativa",
      "00",
      "",
      "0",
      "REMUNERACIONES",
      "002",
      "REMUNERACIONES EVENTUALES",
      "00202",
      "RECARGO DE FUNCIONES",
      "1",
      "GASTOS CORRIENTES",
      "11",
      "GASTOS DE CONSUMO",
      "111",
      "REMUNERACIONES",
      "1111",
      "SUELDOS Y SALARIOS",
      "1",
      "FUNCIONES DE SERVICIOS PUBLICOS GENERALES",
      "11",
      "SERVICIOS PUBLICOS GENERALES",
      "112",
      "AYUDA ECONOMICA EXTERIOR",
      "1120",
      "AYUDA ECONOMICA EXTERIOR",
      "001",
      "Ingresos Corrientes",
      "Ingresos Corrientes",
      "INTERNO",
      "10000000.00",
      "10000000.00",
      "10000000.00",
      "0.00",
      "0.00",
      "0.00",
      "0.00",
      "0.00"
    ],
    [
      "2018",
      "10",
      "101",
      "Asamblea Legislativa",
      "002",
      "Asamblea Legislativa",
      "00",
      "",
      "0",
      "REMUNERACIONES",
      "002",
      "REMUNERACIONES EVENTUALES",
      "00202",
      "RECARGO DE FUNCIONES",
      "1",
      "GASTOS CORRIENTES",
      "11",
      "GASTOS DE CONSUMO",
      "111",
      "REMUNERACIONES",
      "1111",
      "SUELDOS Y SALARIOS",
      "1",
      "FUNCIONES DE SERVICIOS PUBLICOS GENERALES",
      "11",
      "SERVICIOS PUBLICOS GENERALES",
      "112",
      "AYUDA ECONOMICA EXTERIOR",
      "1120",
      "AYUDA ECONOMICA EXTERIOR",
      "001",
      "Ingresos Corrientes",
      "Ingresos Corrientes",
      "INTERNO",
      "10000000.00",
      "10000000.00",
      "10000000.00",
      "0.00",
      "0.00",
      "0.00",
      "0.00",
      "0.00"
    ],
    [
      "2018",
      "11",
      "101",
      "Asamblea Legislativa",
      "002",
      "Asamblea Legislativa",
      "00",
      "",
      "0",
      "REMUNERACIONES",
      "002",
      "REMUNERACIONES EVENTUALES",
      "00202",
      "RECARGO DE FUNCIONES",
      "1",
      "GASTOS CORRIENTES",
      "11",
      "GASTOS DE CONSUMO",
      "111",
      "REMUNERACIONES",
      "1111",
      "SUELDOS Y SALARIOS",
      "1",
      "FUNCIONES DE SERVICIOS PUBLICOS GENERALES",
      "11",
      "SERVICIOS PUBLICOS GENERALES",
      "112",
      "AYUDA ECONOMICA EXTERIOR",
      "1120",
      "AYUDA ECONOMICA EXTERIOR",
      "001",
      "Ingresos Corrientes",
      "Ingresos Corrientes",
      "INTERNO",
      "10000000.00",
      "10000000.00",
      "10000000.00",
      "0.00",
      "0.00",
      "0.00",
      "0.00",
      "0.00"
    ],
    [
      "2018",
      "12",
      "101",
      "Asamblea Legislativa",
      "002",
      "Asamblea Legislativa",
      "00",
      "",
      "0",
      "REMUNERACIONES",
      "002",
      "REMUNERACIONES EVENTUALES",
      "00202",
      "RECARGO DE FUNCIONES",
      "1",
      "GASTOS CORRIENTES",
      "11",
      "GASTOS DE CONSUMO",
      "111",
      "REMUNERACIONES",
      "1111",
      "SUELDOS Y SALARIOS",
      "1",
      "FUNCIONES DE SERVICIOS PUBLICOS GENERALES",
      "11",
      "SERVICIOS PUBLICOS GENERALES",
      "112",
      "AYUDA ECONOMICA EXTERIOR",
      "1120",
      "AYUDA ECONOMICA EXTERIOR",
      "001",
      "Ingresos Corrientes",
      "Ingresos Corrientes",
      "INTERNO",
      "10000000.00",
      "10000000.00",
      "10000000.00",
      "0.00",
      "0.00",
      "0.00",
      "0.00",
      "0.00"
    ],
    [
      "2018",
      "01",
      "101",
      "Asamblea Legislativa",
      "002",
      "Asamblea Legislativa",
      "00",
      "",
      "0",
      "REMUNERACIONES",
      "002",
      "REMUNERACIONES EVENTUALES",
      "00205",
      "DIETAS",
      "1",
      "GASTOS CORRIENTES",
      "11",
      "GASTOS DE CONSUMO",
      "111",
      "REMUNERACIONES",
      "1111",
      "SUELDOS Y SALARIOS",
      "1",
      "FUNCIONES DE SERVICIOS PUBLICOS GENERALES",
      "11",
      "SERVICIOS PUBLICOS GENERALES",
      "112",
      "AYUDA ECONOMICA EXTERIOR",
      "1120",
      "AYUDA ECONOMICA EXTERIOR",
      "001",
      "Ingresos Corrientes",
      "Ingresos Corrientes",
      "INTERNO",
      "2030000000.00",
      "2030000000.00",
      "2030000000.00",
      "0.00",
      "0.00",
      "0.00",
      "158503650.45",
      "158503650.45"
    ]
  ]
}